upgrade_policy_optimizer-0.1.1.dist-info/licenses/LICENSE
upo/__init__.py
upo/_version.py
upo/cli.py
upo/json_solver.py
upo/mdp.py
upo/result.py
upo/solver.py
upo/validate.py
upgrade_policy_optimizer-0.1.1.dist-info/METADATA
upgrade_policy_optimizer-0.1.1.dist-info/WHEEL
upgrade_policy_optimizer-0.1.1.dist-info/entry_points.txt
upgrade_policy_optimizer-0.1.1.dist-info/top_level.txt
upgrade_policy_optimizer-0.1.1.dist-info/RECORD
